Boris/NetSocks.py
Boris/Shaper.py
Boris/__init__.py
Boris_Ext-1.2.dist-info/METADATA
Boris_Ext-1.2.dist-info/WHEEL
Boris_Ext-1.2.dist-info/top_level.txt
Boris_Ext-1.2.dist-info/RECORD
