Metadata-Version: 2.1
Name: Boris-Ext
Version: 1.2
Summary: Import package for Boris Netsocks
Home-page: https://github.com/SerbanL/Boris2/tree/master/PythonScripting/Netsocks.py
Author: Serban Lepadatu
Author-email: SLepadatu@uclan.ac.uk
License: BSD 2-clause
Platform: UNKNOWN
Classifier: Development Status :: 1 - Planning
Classifier: Intended Audience :: Science/Research
Classifier: License :: OSI Approved :: BSD License
Classifier: Operating System :: POSIX :: Linux
Classifier: Programming Language :: Python :: 3
Classifier: Programming Language :: Python :: 3.4
Classifier: Programming Language :: Python :: 3.5
Classifier: Programming Language :: Python :: 3.8
Requires-Dist: mpi4py (>=2.0)
Requires-Dist: numpy
Requires-Dist: matplotlib
Requires-Dist: more-itertools
